{"inkVersion":21,"root":[["^The alarm <i>buzzes</i>, pulling you from sleep. The scent of <color=brown>coffee</color> fills the air as you prepare for the day ahead. The birds chirping outside your window, a reminder: the early bird gets the worm.","\n","^You gather your things and head out the door, ready or not, for another day at the office, hoping that today is the day you will meet your deadline and finish the project.","\n","ev","str","^Head to work","/str","/ev",{"*":"0.c-0","flg":4},{"c-0":["^ ","\n","ev",{"VAR?":"clickCounter"},1,"+",{"VAR=":"clickCounter","re":true},"/ev",{"->":"office_morning"},{"->":"0.g-0"},{"#f":5}],"g-0":["done",{"#f":5}]}],"done",{"office_morning":["ev",false,"/ev",{"VAR=":"projectCompleted","re":true},"ev",{"VAR?":"dayCounter"},0,"==","/ev",[{"->":".^.b","c":true},{"b":["^  Today is <color=red> Monday </color>",{"->":".^.^.^.10"},null]}],"nop","\n","ev",{"VAR?":"dayCounter"},1,"==","/ev",[{"->":".^.b","c":true},{"b":["^  Today is <color=blue> Tuesday</color>",{"->":".^.^.^.18"},null]}],"nop","\n","ev",{"VAR?":"dayCounter"},2,"==","/ev",[{"->":".^.b","c":true},{"b":["^  Today is <color=yellow> Wednesday</color>",{"->":".^.^.^.26"},null]}],"nop","\n","ev",{"VAR?":"dayCounter"},3,"==","/ev",[{"->":".^.b","c":true},{"b":["^  Today is <color=brown> Thursday</color>",{"->":".^.^.^.34"},null]}],"nop","\n","ev",{"VAR?":"dayCounter"},4,"==","/ev",[{"->":".^.b","c":true},{"b":["^  Today is <color=purple> Friday </color>",{"->":".^.^.^.42"},null]}],"nop","\n","ev",{"VAR?":"dayCounter"},5,"==","/ev",[{"->":".^.b","c":true},{"b":["^  Today is <color=orange> Saturday </color>",{"->":".^.^.^.50"},null]}],"nop","\n","ev",{"VAR?":"dayCounter"},6,"==","/ev",[{"->":".^.b","c":true},{"b":["^  Today is <color=black> Sunday </color>",{"->":".^.^.^.58"},null]}],"nop","\n","ev",{"VAR?":"dayCounter"},5,">=","/ev",[{"->":".^.b","c":true},{"b":["\n","^You arrive at the office, <color=brown>coffee</color> in hand.","\n","^The lights are off. The doors are locked.","\n","^<i>It's the weekend.</i>","\n","^You think...\"How did this happen? What shall I do instead?\"","\n",{"->":"weekend_activities"},{"->":".^.^.^.67"},null]}],[{"->":".^.b"},{"b":["\n","^You arrive at the office, <color=brown>coffee</color> in hand. Another day, another project to complete.","\n",{"->":"work_choices"},{"->":".^.^.^.67"},null]}],"nop","\n",{"#f":1}],"work_choices":[["^You think to yourself... \"Where do I start?\"","\n","ev","str","^Check emails","/str","/ev",{"*":".^.c-0","flg":20},"ev","str","^Start working on the project","/str","/ev",{"*":".^.c-1","flg":20},"ev","str","^Chat with a coworker","/str","/ev",{"*":".^.c-2","flg":20},{"*":".^.c-3","flg":8},{"c-0":["^ ","\n","ev",{"VAR?":"clickCounter"},1,"+",{"VAR=":"clickCounter","re":true},"/ev",{"->":"check_emails"},{"#f":5}],"c-1":["^ ","\n","ev",{"VAR?":"clickCounter"},1,"+",{"VAR=":"clickCounter","re":true},"/ev",{"->":"start_project"},{"#f":5}],"c-2":["^ ","\n","ev",{"VAR?":"clickCounter"},1,"+",{"VAR=":"clickCounter","re":true},"/ev",{"->":"chat_with_coworker"},{"#f":5}],"c-3":["\n","^Today is the day you are going to make <i>good</i> choices and finally finish the project.","\n","ev",{"VAR?":"clickCounter"},1,"+",{"VAR=":"clickCounter","re":true},"/ev",{"->":"start_project"},{"#f":5}]}],{"#f":1}],"check_emails":["^You spend some time reading emails, but get distracted by unimportant messages.","\n","^It seems that the company is planning a lot of social events that you really don't want to take part in. But it is always good to be a team player.","\n",{"->":"midday"},{"#f":1}],"start_project":[["^You sit down and focus on the project. The initial tasks are straightforward, but soon you hit a challenge.","\n",["ev","visit",3,"seq","/ev","ev","du",0,"==","/ev",{"->":".^.s0","c":true},"ev","du",1,"==","/ev",{"->":".^.s1","c":true},"ev","du",2,"==","/ev",{"->":".^.s2","c":true},"nop",{"s0":["pop","^The requirement for the document is unclear.",{"->":".^.^.23"},null],"s1":["pop","^ The software crashes unexpectedly.",{"->":".^.^.23"},null],"s2":["pop","^Your supervisor emails asking for an update sooner than expected.",{"->":".^.^.23"},null],"#f":5}],"\n","ev","str","^Break down the task into smaller parts","/str","/ev",{"*":".^.c-0","flg":4},"ev","str","^Try to power through without a plan","/str","/ev",{"*":".^.c-1","flg":4},{"c-0":["^ ","\n","ev",{"VAR?":"clickCounter"},1,"+",{"VAR=":"clickCounter","re":true},"/ev",{"->":"break_down_task"},{"#f":5}],"c-1":["^ ","\n","ev",{"VAR?":"clickCounter"},1,"+",{"VAR=":"clickCounter","re":true},"/ev",{"->":"no_plan"},{"#f":5}]}],{"#f":1}],"break_down_task":["^You methodically tackle each part, making steady progress.","\n","^Pretty proud of yourself, it's almost lunch time.","\n","ev",true,"/ev",{"VAR=":"projectCompleted","re":true},{"->":"midday"},{"#f":1}],"no_plan":["^You work frantically, but hit a roadblock and lose time.","\n","^Thinking you should have broken down the work into smaller tasks, you rethink what you might be able to accomplish in the afternoon, but now lunch is approaching.","\n",{"->":"midday"},{"#f":1}],"chat_with_coworker":[["^<color=purple>Jennie</color> sits down next to you. She starts in on the gossip. As <color=purple>Jennie</color> talks you think about the work you have to get done today and rethink your decision to chat with her.","\n","ev","str","^A Few Moments Later","/str","/ev",{"*":".^.c-0","flg":4},{"c-0":["^ ","\n","ev",{"VAR?":"clickCounter"},1,"+",{"VAR=":"clickCounter","re":true},"/ev","^Time flies when you aren't working on the project. You realize you have been talking longer than usual.","\n","^The deadline keeps approaching, and the work isn't done. It's almost the afternoon.","\n",{"->":"midday"},{"#f":5}]}],{"#f":1}],"midday":[["^It's lunchtime. The office hums with the sounds of chatter. Everyone begins to make their way to the lunch room.","\n","ev","str","^Eat in the lunch room with co-workers","/str","/ev",{"*":".^.c-0","flg":4},"ev","str","^Eat lunch at desk and continue working","/str","/ev",{"*":".^.c-1","flg":4},"ev","str","^Go out for lunch","/str","/ev",{"*":".^.c-2","flg":4},{"c-0":["^ ","\n","ev",{"VAR?":"clickCounter"},1,"+",{"VAR=":"clickCounter","re":true},"/ev",{"->":"lunch_with_coworkers"},{"#f":5}],"c-1":["^ ","\n","ev",{"VAR?":"clickCounter"},1,"+",{"VAR=":"clickCounter","re":true},"/ev",{"->":"lunch_at_desk"},{"#f":5}],"c-2":["^ ","\n","ev",{"VAR?":"clickCounter"},1,"+",{"VAR=":"clickCounter","re":true},"/ev",{"->":"lunch_outside"},{"#f":5}]}],{"#f":1}],"lunch_with_coworkers":["^Listening to the gossip, you really don't want to get involved.","\n","^But the conversation is intriguing, so you stay until the hour is over, then head back to your desk.","\n",{"->":"afternoon"},{"#f":1}],"lunch_at_desk":["^You power through the afternoon, tuning out any distractions that might come up.","\n","ev",true,"/ev",{"VAR=":"projectCompleted","re":true},{"->":"afternoon"},{"#f":1}],"lunch_outside":["ev",{"VAR?":"projectCompleted"},"/ev",[{"->":".^.b","c":true},{"b":["\n","^Feeling accomplished, you decide to take a quick nap. Unfortunately, you fall asleep and wake up to find the parking lot almost empty.","\n","ev","str","^Hurry back to your desk","/str","/ev",{"*":".^.c-0","flg":4},{"->":".^.^.^.5"},{"c-0":["^ ","\n","ev",{"VAR?":"clickCounter"},1,"+",{"VAR=":"clickCounter","re":true},"/ev",{"->":"end_of_day"},{"#f":5}]}]}],[{"->":".^.b"},{"b":["\n","^You take a real break and clear your mind, but lose valuable time.","\n",{"->":"afternoon"},{"->":".^.^.^.5"},null]}],"nop","\n",{"#f":1}],"afternoon":[["^The afternoon slump hits. You struggle to stay focused. Only a few hours are left in the day, and you know you can make it through.","\n","ev","str","^Push through and work hard","/str","/ev",{"*":".^.c-0","flg":4},"ev","str","^Get another coffee","/str","/ev",{"*":".^.c-1","flg":4},{"c-0":["\n","ev",{"VAR?":"clickCounter"},1,"+",{"VAR=":"clickCounter","re":true},"/ev",{"->":"push_through"},{"#f":5}],"c-1":["\n","ev",{"VAR?":"clickCounter"},1,"+",{"VAR=":"clickCounter","re":true},"/ev",{"->":"coffee_break"},{"#f":5}]}],{"#f":1}],"push_through":[["^You make some progress and are feeling good, however the deadline still looms, and the day is coming to an end.","\n","ev","str","^You hope you finish in time","/str","/ev",{"*":".^.c-0","flg":4},{"c-0":["^ ",{"->":"end_of_day"},"\n",{"#f":5}]}],{"#f":1}],"coffee_break":[["^<color=purple>Jennie</color> (<i>the chatty co-worker</i>) happens to be in the break room. She starts talking about how she is finished with her work, which reminds you about the pile of work on your desk.","\n","ev","str","^Drink the coffee","/str","/ev",{"*":".^.c-0","flg":4},{"c-0":["\n","ev",{"VAR?":"clickCounter"},1,"+",{"VAR=":"clickCounter","re":true},"/ev","^You drink your <color=brown>coffee</color> as you walk back to your office.","\n","^The caffeine kicks in, but you’re still working on the project hoping you have enough time as the end of the day nears.","\n",["ev","str","^The Day is Over","/str","/ev",{"*":".^.c-0","flg":4},{"c-0":["^ ","\n","ev",{"VAR?":"clickCounter"},1,"+",{"VAR=":"clickCounter","re":true},"/ev",{"->":"end_of_day"},{"#f":5}]}],{"#f":5}]}],{"#f":1}],"end_of_day":["ev",{"VAR?":"projectCompleted"},"/ev",[{"->":".^.b","c":true},{"b":["\n","^Your project is finished. You can finally go home feeling satisfied.","\n","^Total choices needed to finish project: ","ev",{"VAR?":"clickCounter"},"out","/ev","\n","end",{"->":".^.^.^.5"},null]}],[{"->":".^.b"},{"b":["\n","^You didn’t finish your project. You’ll have to try again tomorrow and make <i>better</i> choices if you want to feel accomplished.","\n","ev","str","^Go Home","/str","/ev",{"*":".^.c-0","flg":4},{"->":".^.^.^.5"},{"c-0":["\n","ev",false,"/ev",{"VAR=":"projectCompleted","re":true},"ev",{"VAR?":"dayCounter"},1,"+",7,"%","/ev",{"VAR=":"dayCounter","re":true},{"->":"office_morning"},{"#f":5}]}]}],"nop","\n",{"#f":1}],"weekend_activities":[["^You take the weekend off.","\n","^Maybe some rest will help you be more productive next week.","\n","ev","str","^Relax at home","/str","/ev",{"*":".^.c-0","flg":4},"ev","str","^Go out with friends","/str","/ev",{"*":".^.c-1","flg":4},{"c-0":["^ ","\n","ev",{"VAR?":"clickCounter"},1,"+",{"VAR=":"clickCounter","re":true},"/ev",{"->":"next_day"},{"#f":5}],"c-1":["\n","ev",{"VAR?":"clickCounter"},1,"+",{"VAR=":"clickCounter","re":true},"/ev",{"->":"next_day"},{"#f":5}]}],{"#f":1}],"next_day":["ev",{"VAR?":"dayCounter"},1,"+",7,"%","/ev",{"VAR=":"dayCounter","re":true},{"->":"office_morning"},{"#f":1}],"global decl":["ev",false,{"VAR=":"projectCompleted"},0,{"VAR=":"dayCounter"},0,{"VAR=":"clickCounter"},"/ev","end",null],"#f":1}],"listDefs":{}}